.gitignore
.gitlab-ci.yml
CHANGELOG.md
CMakeLists.txt
COPYING
INSTALL
LICENSE.md
README.md
config.h.cmake
dune-istl.pc.in
dune.module
pyproject.toml
setup.py
LICENSES/LicenseRef-GPL-2.0-only-with-DUNE-exception.txt
cmake/modules/AddARPACKPPFlags.cmake
cmake/modules/AddSuperLUFlags.cmake
cmake/modules/CMakeLists.txt
cmake/modules/DuneIstlMacros.cmake
cmake/modules/FindARPACK.cmake
cmake/modules/FindARPACKPP.cmake
cmake/modules/FindSuperLU.cmake
doc/CMakeLists.txt
doc/blockstructure.eps
doc/blockstructure.eps.license
doc/istl.bib
doc/istl.tex
doc/doxygen/CMakeLists.txt
doc/doxygen/Doxylocal
doc/doxygen/mainpage.txt
doc/doxygen/modules.txt
dune/CMakeLists.txt
dune/istl/CMakeLists.txt
dune/istl/allocator.hh
dune/istl/basearray.hh
dune/istl/bccsmatrix.hh
dune/istl/bccsmatrixinitializer.hh
dune/istl/bcrsmatrix.hh
dune/istl/bdmatrix.hh
dune/istl/blocklevel.hh
dune/istl/btdmatrix.hh
dune/istl/bvector.hh
dune/istl/cholmod.hh
dune/istl/dilu.hh
dune/istl/foreach.hh
dune/istl/gsetc.hh
dune/istl/ildl.hh
dune/istl/ilu.hh
dune/istl/ilusubdomainsolver.hh
dune/istl/io.hh
dune/istl/istlexception.hh
dune/istl/ldl.hh
dune/istl/matrix.hh
dune/istl/matrixindexset.hh
dune/istl/matrixmarket.hh
dune/istl/matrixmatrix.hh
dune/istl/matrixredistribute.hh
dune/istl/matrixutils.hh
dune/istl/multitypeblockmatrix.hh
dune/istl/multitypeblockvector.hh
dune/istl/novlpschwarz.hh
dune/istl/operators.hh
dune/istl/overlappingschwarz.hh
dune/istl/owneroverlapcopy.hh
dune/istl/preconditioner.hh
dune/istl/preconditioners.hh
dune/istl/repartition.hh
dune/istl/scalarproducts.hh
dune/istl/scaledidmatrix.hh
dune/istl/schwarz.hh
dune/istl/solver.hh
dune/istl/solvercategory.hh
dune/istl/solverfactory.hh
dune/istl/solverregistry.hh
dune/istl/solvers.hh
dune/istl/solvertype.hh
dune/istl/spqr.hh
dune/istl/superlu.hh
dune/istl/superlufunctions.hh
dune/istl/supermatrix.hh
dune/istl/umfpack.hh
dune/istl/vbvector.hh
dune/istl/common/CMakeLists.txt
dune/istl/common/counter.hh
dune/istl/common/registry.hh
python/dune_istl.egg-info/PKG-INFO
python/dune_istl.egg-info/SOURCES.txt
python/dune_istl.egg-info/dependency_links.txt
python/dune_istl.egg-info/requires.txt
python/dune_istl.egg-info/top_level.txt
