Metadata-Version: 2.1
Name: dune-istl
Version: 2.11.dev20250709
Summary: Iterative solver template library which provides generic sparse matrix/vector classes and a variety of solvers based on these classes
Home-page: https://gitlab.dune-project.org/core/dune-istl
Author: The Dune Core developers
Author-email: dune-devel@lists.dune-project.org
Classifier: Programming Language :: C++
Classifier: Programming Language :: Python :: 3
Classifier: License :: OSI Approved :: GNU General Public License (GPL)
Requires-Python: >=3.4
License-File: LICENSE.md
License-File: COPYING
